qmodel/__init__.py
qmodel/model_common.py
qmodel/model_testing.py
qmodel/model_training.py
qmodel/model_using.py
qmodel/prediction_images.py
qmodel/test_model_testing.py
qmodel/test_model_training.py
qmodel/test_prediction_images.py
qmodel/test_testing_set.py
qmodel/test_training_set.py
qmodel/testing_set.py
qmodel/tools.py
qmodel/training_set.py
qmodel-1.0.1.dist-info/LICENSE
qmodel-1.0.1.dist-info/METADATA
qmodel-1.0.1.dist-info/WHEEL
qmodel-1.0.1.dist-info/top_level.txt
qmodel-1.0.1.dist-info/RECORD
